{"cameraMode":{"drawMode":0,"name":"Shaded","section":"Shading Mode"},"sceneLighting":true,"audioPlay":false,"sceneViewState":{"showFog":true,"showMaterialUpdate":false,"showSkybox":true,"showFlares":true,"showImageEffects":true,"showParticleSystems":true,"showVisualEffectGraphs":true,"m_FxEnabled":true},"in2DMode":false,"pivot":{"x":-3.8356337547302248,"y":1.187000036239624,"z":-1.3300000429153443},"rotation":{"x":0.06673867255449295,"y":0.9332576394081116,"z":-0.24807633459568025,"w":0.2510674297809601},"size":5.216217994689941,"orthographic":false}